_nncase.cpython-39-x86_64-linux-gnu.so
libNncase.Runtime.Native.so
nncase/DryIoc.Microsoft.DependencyInjection.dll
nncase/DryIoc.dll
nncase/Extension.Mathematics.dll
nncase/FlatBuffers.dll
nncase/GiGraph.Dot.Entities.dll
nncase/GiGraph.Dot.Output.Generators.dll
nncase/GiGraph.Dot.Output.Writers.dll
nncase/GiGraph.Dot.Output.dll
nncase/GiGraph.Dot.Types.dll
nncase/GiGraph.Dot.dll
nncase/Google.OrTools.dll
nncase/Google.Protobuf.dll
nncase/LanguageExt.Core.dll
nncase/Microsoft.Bcl.AsyncInterfaces.dll
nncase/Microsoft.Extensions.Configuration.Abstractions.dll
nncase/Microsoft.Extensions.Configuration.Binder.dll
nncase/Microsoft.Extensions.Configuration.CommandLine.dll
nncase/Microsoft.Extensions.Configuration.EnvironmentVariables.dll
nncase/Microsoft.Extensions.Configuration.FileExtensions.dll
nncase/Microsoft.Extensions.Configuration.Json.dll
nncase/Microsoft.Extensions.Configuration.UserSecrets.dll
nncase/Microsoft.Extensions.Configuration.dll
nncase/Microsoft.Extensions.DependencyInjection.Abstractions.dll
nncase/Microsoft.Extensions.DependencyInjection.dll
nncase/Microsoft.Extensions.FileProviders.Abstractions.dll
nncase/Microsoft.Extensions.FileProviders.Physical.dll
nncase/Microsoft.Extensions.FileSystemGlobbing.dll
nncase/Microsoft.Extensions.Hosting.Abstractions.dll
nncase/Microsoft.Extensions.Hosting.dll
nncase/Microsoft.Extensions.Logging.Abstractions.dll
nncase/Microsoft.Extensions.Logging.Configuration.dll
nncase/Microsoft.Extensions.Logging.Console.dll
nncase/Microsoft.Extensions.Logging.Debug.dll
nncase/Microsoft.Extensions.Logging.EventLog.dll
nncase/Microsoft.Extensions.Logging.EventSource.dll
nncase/Microsoft.Extensions.Logging.dll
nncase/Microsoft.Extensions.Options.ConfigurationExtensions.dll
nncase/Microsoft.Extensions.Options.dll
nncase/Microsoft.Extensions.Primitives.dll
nncase/Microsoft.Toolkit.HighPerformance.dll
nncase/NetFabric.Hyperlinq.Abstractions.dll
nncase/NetFabric.Hyperlinq.dll
nncase-2.10.0.dist-info/METADATA
nncase-2.10.0.dist-info/WHEEL
nncase-2.10.0.dist-info/top_level.txt
nncase-2.10.0.dist-info/RECORD
nncase-2.10.0.dist-info/licenses/LICENSE
