Metadata-Version: 2.4
Name: nncase
Version: 2.10.0
Summary: A neural network compiler for AI accelerators
Author: sunnycase
Author-email: sunnycase@live.cn
Maintainer: sunnycase
Maintainer-email: sunnycase@live.cn
License: 
Project-URL: homepage, https://github.com/kendryte/nncase
Keywords: kendryte,nn,compiler,k210,k510,k230
Classifier: Programming Language :: C++
Classifier: Programming Language :: Python :: 3
Classifier: Programming Language :: Python :: 3.9
Classifier: Programming Language :: Python :: 3.10
Classifier: Programming Language :: Python :: 3.11
Classifier: Programming Language :: Python :: 3.12
Classifier: Programming Language :: Python :: 3.13
Classifier: License :: OSI Approved :: Apache Software License
Classifier: Operating System :: OS Independent
Requires-Python: >=3.9
License-File: LICENSE
Requires-Dist: numpy
Dynamic: license-file
